BinomoAPI/__init__.py
BinomoAPI/api.py
BinomoAPI/assets.json
BinomoAPI/config_manager.py
BinomoAPI/constants.py
BinomoAPI/exceptions.py
BinomoAPI/global_values.py
BinomoAPI/models.py
BinomoAPI/config/__init_.py
BinomoAPI/config/conf.py
BinomoAPI/wss/__init__.py
BinomoAPI/wss/client.py
BinomoAPI/wss/enhanced_client.py
binomoapi-2.0.0.dist-info/licenses/LICENSE
binomoapi-2.0.0.dist-info/METADATA
binomoapi-2.0.0.dist-info/WHEEL
binomoapi-2.0.0.dist-info/top_level.txt
binomoapi-2.0.0.dist-info/RECORD
