Metadata-Version: 2.4
Name: BinomoAPI
Version: 2.0.0
Summary: Professional Python client for Binomo trading platform
Author-email: ChipaDevTeam <chipadevteam@gmail.com>
License: MIT License
Project-URL: Homepage, https://github.com/ChipaDevTeam/BinomoAPI
Project-URL: Documentation, https://github.com/ChipaDevTeam/BinomoAPI/blob/main/README.md
Project-URL: Repository, https://github.com/ChipaDevTeam/BinomoAPI
Project-URL: Bug Reports, https://github.com/ChipaDevTeam/BinomoAPI/issues
Project-URL: Source Code, https://github.com/ChipaDevTeam/BinomoAPI
Keywords: binomo,trading,binary options,api,finance,investment
Classifier: Development Status :: 4 - Beta
Classifier: Intended Audience :: Developers
Classifier: Intended Audience :: Financial and Insurance Industry
Classifier: License :: OSI Approved :: MIT License
Classifier: Operating System :: OS Independent
Classifier: Programming Language :: Python :: 3
Classifier: Programming Language :: Python :: 3.8
Classifier: Programming Language :: Python :: 3.9
Classifier: Programming Language :: Python :: 3.10
Classifier: Programming Language :: Python :: 3.11
Classifier: Programming Language :: Python :: 3.12
Classifier: Topic :: Office/Business :: Financial :: Investment
Classifier: Topic :: Software Development :: Libraries :: Python Modules
Requires-Python: >=3.8
License-File: LICENSE
Requires-Dist: requests>=2.31.0
Requires-Dist: websockets>=11.0.0
Requires-Dist: aiohttp>=3.8.0
Requires-Dist: dataclasses-json>=0.6.0
Requires-Dist: typing-extensions>=4.5.0
Provides-Extra: dev
Requires-Dist: pytest>=7.0.0; extra == "dev"
Requires-Dist: pytest-asyncio>=0.21.0; extra == "dev"
Requires-Dist: black>=23.0.0; extra == "dev"
Requires-Dist: flake8>=6.0.0; extra == "dev"
Requires-Dist: mypy>=1.0.0; extra == "dev"
Requires-Dist: build>=0.10.0; extra == "dev"
Requires-Dist: twine>=4.0.0; extra == "dev"
Dynamic: license-file
